yamlfig/__init__.py
yamlfig/__version__.py
yamlfig/base.py
yamlfig/test.py
yamlfig-1.0.0.dist-info/LICENSE.txt
yamlfig-1.0.0.dist-info/METADATA
yamlfig-1.0.0.dist-info/WHEEL
yamlfig-1.0.0.dist-info/entry_points.txt
yamlfig-1.0.0.dist-info/top_level.txt
yamlfig-1.0.0.dist-info/RECORD
