Metadata-Version: 2.1
Name: yamlfig
Version: 1.0.0
Summary: Verify the structure of YAML-formatted configuration files.
Home-page: https://github.com/ktkalaru/yamlfig
Author: ktkalaru
Author-email: ktkalaru+yamlfig@gmail.com
License: MIT
Keywords: config-file,validation,yaml
Platform: any
Classifier: Development Status :: 3 - Alpha
Classifier: License :: OSI Approved :: MIT License
Classifier: Intended Audience :: Developers
Classifier: Operating System :: OS Independent
Classifier: Programming Language :: Python :: 2
Classifier: Programming Language :: Python :: 2.7
Classifier: Programming Language :: Python :: 3
Classifier: Programming Language :: Python :: 3.5
Classifier: Programming Language :: Python :: 3.6
Classifier: Programming Language :: Python :: 3.7
Classifier: Topic :: Software Development :: Libraries
Classifier: Topic :: Text Processing :: Markup
Requires-Python: >=2.7, !=3.0, !=3.1, !=3.2, !=3.3, !=3.4, <4
Requires-Dist: pyyaml
